rblxpy/__init__.py
rblxpy-0.0.2.dist-info/LICENSE
rblxpy-0.0.2.dist-info/METADATA
rblxpy-0.0.2.dist-info/WHEEL
rblxpy-0.0.2.dist-info/top_level.txt
rblxpy-0.0.2.dist-info/RECORD
