Metadata-Version: 2.1
Name: rblxpy
Version: 0.0.2
Summary: A ROBLOX Python package
Home-page: UNKNOWN
Author: INfoUpgraders
Author-email: infoupgraders@gmail.com
License: UNKNOWN
Platform: UNKNOWN
Classifier: Programming Language :: Python :: 3
Classifier: License :: OSI Approved :: MIT License
Classifier: Operating System :: OS Independent
Requires-Python: >=3.8
